{"cameraMode":{"drawMode":0,"name":"Shaded","section":"Shading Mode"},"sceneLighting":false,"audioPlay":false,"sceneViewState":{"m_AlwaysRefresh":false,"showFog":true,"showSkybox":false,"showFlares":true,"showImageEffects":true,"showParticleSystems":true,"showVisualEffectGraphs":true,"m_FxEnabled":true},"in2DMode":false,"pivot":{"x":0.0,"y":0.24986149370670319,"z":8.867770195007325},"rotation":{"x":0.07161767780780792,"y":0.18149778246879579,"z":-0.013258848339319229,"w":0.9806936979293823},"size":0.7091032266616821,"orthographic":true}